README.rst
setup.py
bond_zlj/__init__.py
bond_zlj/basic_classes.py
bond_zlj/functions.py
bond_zlj.egg-info/PKG-INFO
bond_zlj.egg-info/SOURCES.txt
bond_zlj.egg-info/dependency_links.txt
bond_zlj.egg-info/top_level.txt
bond_zlj.egg-info/zip-safe