Metadata-Version: 1.1
Name: bond-zlj
Version: 0.1.1
Summary: this is a package for bond calculation
Home-page: http://www.baidu.com/
Author: LinjunZhou
Author-email: zhoulinjun1994@163.com
License: MIT
Keywords: finance bond calculation
Platform: UNKNOWN
Classifier: License :: OSI Approved :: MIT License
Classifier: Programming Language :: Python
Classifier: Intended Audience :: Developers
Classifier: Operating System :: OS Independent
